pyboomi_platform/__init__.py
pyboomi_platform/auth.py
pyboomi_platform/client.py
pyboomi_platform/config.py
pyboomi_platform/exceptions.py
pyboomi_platform/utils.py
pyboomi_platform-0.1.0.dist-info/licenses/LICENSE
pyboomi_platform-0.1.0.dist-info/METADATA
pyboomi_platform-0.1.0.dist-info/WHEEL
pyboomi_platform-0.1.0.dist-info/top_level.txt
pyboomi_platform-0.1.0.dist-info/RECORD
