Metadata-Version: 2.4
Name: pyboomi_platform
Version: 0.1.0
Summary: Python SDK for interacting with the Boomi Platform API
Author-email: Robert Little <robert@iesoftwaredeveloper.com>
Maintainer-email: Robert Little <robert@iesoftwaredeveloper.com>
License-Expression: Apache-2.0
Project-URL: Homepage, https://github.com/iesoftwaredeveloper/pyboomi-platform
Project-URL: Documentation, https://github.com/iesoftwaredeveloper/pyboomi-platform#readme
Project-URL: Repository, https://github.com/iesoftwaredeveloper/pyboomi-platform.git
Project-URL: Changelog, https://github.com/iesoftwaredeveloper/pyboomi-platform/blob/main/CHANGELOG.md
Keywords: boomi,integration,api,sdk
Classifier: Development Status :: 3 - Alpha
Classifier: Intended Audience :: Developers
Classifier: Operating System :: OS Independent
Classifier: Programming Language :: Python :: 3
Classifier: Programming Language :: Python :: 3.8
Classifier: Programming Language :: Python :: 3.9
Classifier: Programming Language :: Python :: 3.10
Classifier: Programming Language :: Python :: 3.11
Classifier: Programming Language :: Python :: 3.12
Classifier: Topic :: Software Development :: Libraries :: Python Modules
Classifier: Topic :: System :: Systems Administration
Requires-Python: >=3.8
License-File: LICENSE
Requires-Dist: requests>=2.28.0
Requires-Dist: PyYAML>=6.0
Dynamic: license-file
